earthquake_detection/__init__.py
detectearthquakeindonesia-0.1.1.dist-info/LICENSE
detectearthquakeindonesia-0.1.1.dist-info/METADATA
detectearthquakeindonesia-0.1.1.dist-info/WHEEL
detectearthquakeindonesia-0.1.1.dist-info/top_level.txt
detectearthquakeindonesia-0.1.1.dist-info/RECORD
